[
    {
      "id": 11,
      "name": "Pikachu",
      "types": ["Electric"]
    },
    {
      "id": 10,
      "name": "Gabite",
      "types": ["Dragon", "Ground"]
    },
      {
        "id": 1,
        "name": "Bulbasaur",
        "types": ["Grass", "Poison"]
      },
      {
        "id": 2,
        "name": "Ivysaur",
        "types": ["Grass", "Poison"]
      },
      {
        "id": 3,
        "name": "Venusaur",
        "types": ["Grass", "Poison"]
      },
      {
        "id": 4,
        "name": "Charmander",
        "types": ["Fire"]
      },
      {
        "id": 5,
        "name": "Charmeleon",
        "types": ["Fire"]
      },
      {
        "id": 6,
        "name": "Charizard",
        "types": ["Fire", "Flying"]
      },
      {
        "id": 7,
        "name": "Squirtle",
        "types": ["Water"]
      },
      {
        "id": 8,
        "name": "Wartortle",
        "types": ["Water"]
      },
      {
        "id": 9,
        "name": "Blastoise",
        "types": ["Water"]
      }
]